Workbook
Name Slicer_Age_Group: #N/A
Name Slicer_Payment_Method: #N/A
Name Slicer_Product_Category: #N/A
Name Slicer_Purchase_Month_Name: #N/A

Sheet ecommerce_customer_data_custom_
A1: Customer ID | B1: Purchase Date | C1: Product Category | D1: Product Price | E1: Quantity | F1: Total Purchase Amount | G1: Payment Method | H1: Customer Age | I1: Returns | J1: Gender | K1: Churn | L1: Purchase Year | M1: Purchase Month No | N1: Purchase Month Name | O1: Age Group | P1: Return Flag | Q1: Payment Category
A2: 46251 | B2: 44082.402 | C2: Electronics | D2: 12 | E2: 3 | F2: 740 | G2: Credit Card | H2: 37 | I2: 0 | J2: Male | K2: 0 | L2: =YEAR(ecommerce_customer_data_custom_[[#This Row],[Purchase Date]]) -> 2020 | M2: =MONTH(ecommerce_customer_data_custom_[[#This Row],[Purchase Date]]) -> 9 | N2: =TEXT(ecommerce_customer_data_custom_[[#This Row],[Purchase Date]],"mmmm") -> September | O2: =VLOOKUP(ecommerce_customer_data_custom_[[#This Row],[Customer Age]],AgeGroupMapping!$A$2:$C$5,3,TRUE) -> Adult | P2: =IF(ecommerce_customer_data_custom_[[#This Row],[Returns]]=1,"Returned","Not Returned") -> Not Returned | Q2: =_xlfn.XLOOKUP(ecommerce_customer_data_custom_[[#This Row],[Payment Method]],PaymentMapping!$A$2:$A$11,PaymentMapping!$B$2:$B$11,"Other") -> Card
A3: 46251 | B3: 44625.539 | C3: Home | D3: 468 | E3: 4 | F3: 2739 | G3: PayPal | H3: 37 | I3: 0 | J3: Male | K3: 0 | L3: =YEAR(ecommerce_customer_data_custom_[[#This Row],[Purchase Date]]) -> 2022 | M3: =MONTH(ecommerce_customer_data_custom_[[#This Row],[Purchase Date]]) -> 3 | N3: =TEXT(ecommerce_customer_data_custom_[[#This Row],[Purchase Date]],"mmmm") -> March | O3: =VLOOKUP(ecommerce_customer_data_custom_[[#This Row],[Customer Age]],AgeGroupMapping!$A$2:$C$5,3,TRUE) -> Adult | P3: =IF(ecommerce_customer_data_custom_[[#This Row],[Returns]]=1,"Returned","Not Returned") -> Not Returned | Q3: =_xlfn.XLOOKUP(ecommerce_customer_data_custom_[[#This Row],[Payment Method]],PaymentMapping!$A$2:$A$11,PaymentMapping!$B$2:$B$11,"Other") -> Wallet/UPI
A4: 46251 | B4: 44704.763 | C4: Home | D4: 288 | E4: 2 | F4: 3196 | G4: PayPal | H4: 37 | I4: 0 | J4: Male | K4: 0 | L4: =YEAR(ecommerce_customer_data_custom_[[#This Row],[Purchase Date]]) -> 2022 | M4: =MONTH(ecommerce_customer_data_custom_[[#This Row],[Purchase Date]]) -> 5 | N4: =TEXT(ecommerce_customer_data_custom_[[#This Row],[Purchase Date]],"mmmm") -> May | O4: =VLOOKUP(ecommerce_customer_data_custom_[[#This Row],[Customer Age]],AgeGroupMapping!$A$2:$C$5,3,TRUE) -> Adult | P4: =IF(ecommerce_customer_data_custom_[[#This Row],[Returns]]=1,"Returned","Not Returned") -> Not Returned | Q4: =_xlfn.XLOOKUP(ecommerce_customer_data_custom_[[#This Row],[Payment Method]],PaymentMapping!$A$2:$A$11,PaymentMapping!$B$2:$B$11,"Other") -> Wallet/UPI
A5: 46251 | B5: 44147.551 | C5: Clothing | D5: 196 | E5: 1 | F5: 3509 | G5: PayPal | H5: 37 | I5: 0 | J5: Male | K5: 0 | L5: =YEAR(ecommerce_customer_data_custom_[[#This Row],[Purchase Date]]) -> 2020 | M5: =MONTH(ecommerce_customer_data_custom_[[#This Row],[Purchase Date]]) -> 11 | N5: =TEXT(ecommerce_customer_data_custom_[[#This Row],[Purchase Date]],"mmmm") -> November | O5: =VLOOKUP(ecommerce_customer_data_custom_[[#This Row],[Customer Age]],AgeGroupMapping!$A$2:$C$5,3,TRUE) -> Adult | P5: =IF(ecommerce_customer_data_custom_[[#This Row],[Returns]]=1,"Returned","Not Returned") -> Not Returned | Q5: =_xlfn.XLOOKUP(ecommerce_customer_data_custom_[[#This Row],[Payment Method]],PaymentMapping!$A$2:$A$11,PaymentMapping!$B$2:$B$11,"Other") -> Wallet/UPI
A6: 13593 | B6: 44162.747 | C6: Home | D6: 449 | E6: 1 | F6: 3452 | G6: Credit Card | H6: 49 | I6: 0 | J6: Female | K6: 1 | L6: =YEAR(ecommerce_customer_data_custom_[[#This Row],[Purchase Date]]) -> 2020 | M6: =MONTH(ecommerce_customer_data_custom_[[#This Row],[Purchase Date]]) -> 11 | N6: =TEXT(ecommerce_customer_data_custom_[[#This Row],[Purchase Date]],"mmmm") -> November | O6: =VLOOKUP(ecommerce_customer_data_custom_[[#This Row],[Customer Age]],AgeGroupMapping!$A$2:$C$5,3,TRUE) -> Middle-Aged | P6: =IF(ecommerce_customer_data_custom_[[#This Row],[Returns]]=1,"Returned","Not Returned") -> Not Returned | Q6: =_xlfn.XLOOKUP(ecommerce_customer_data_custom_[[#This Row],[Payment Method]],PaymentMapping!$A$2:$A$11,PaymentMapping!$B$2:$B$11,"Other") -> Card
A7: 13593 | B7: 44992.596 | C7: Home | D7: 250 | E7: 4 | F7: 575 | G7: PayPal | H7: 49 | I7: 1 | J7: Female | K7: 1 | L7: =YEAR(ecommerce_customer_data_custom_[[#This Row],[Purchase Date]]) -> 2023 | M7: =MONTH(ecommerce_customer_data_custom_[[#This Row],[Purchase Date]]) -> 3 | N7: =TEXT(ecommerce_customer_data_custom_[[#This Row],[Purchase Date]],"mmmm") -> March | O7: =VLOOKUP(ecommerce_customer_data_custom_[[#This Row],[Customer Age]],AgeGroupMapping!$A$2:$C$5,3,TRUE) -> Middle-Aged | P7: =IF(ecommerce_customer_data_custom_[[#This Row],[Returns]]=1,"Returned","Not Returned") -> Returned | Q7: =_xlfn.XLOOKUP(ecommerce_customer_data_custom_[[#This Row],[Payment Method]],PaymentMapping!$A$2:$A$11,PaymentMapping!$B$2:$B$11,"Other") -> Wallet/UPI
A8: 13593 | B8: 45031.127 | C8: Electronics | D8: 73 | E8: 1 | F8: 1896 | G8: Credit Card | H8: 49 | I8: 0 | J8: Female | K8: 1 | L8: =YEAR(ecommerce_customer_data_custom_[[#This Row],[Purchase Date]]) -> 2023 | M8: =MONTH(ecommerce_customer_data_custom_[[#This Row],[Purchase Date]]) -> 4 | N8: =TEXT(ecommerce_customer_data_custom_[[#This Row],[Purchase Date]],"mmmm") -> April | O8: =VLOOKUP(ecommerce_customer_data_custom_[[#This Row],[Customer Age]],AgeGroupMapping!$A$2:$C$5,3,TRUE) -> Middle-Aged | P8: =IF(ecommerce_customer_data_custom_[[#This Row],[Returns]]=1,"Returned","Not Returned") -> Not Returned | Q8: =_xlfn.XLOOKUP(ecommerce_customer_data_custom_[[#This Row],[Payment Method]],PaymentMapping!$A$2:$A$11,PaymentMapping!$B$2:$B$11,"Other") -> Card
A9: 13593 | B9: 44282.891 | C9: Books | D9: 337 | E9: 2 | F9: 2937 | G9: Cash | H9: 49 | I9: 0 | J9: Female | K9: 1 | L9: =YEAR(ecommerce_customer_data_custom_[[#This Row],[Purchase Date]]) -> 2021 | M9: =MONTH(ecommerce_customer_data_custom_[[#This Row],[Purchase Date]]) -> 3 | N9: =TEXT(ecommerce_customer_data_custom_[[#This Row],[Purchase Date]],"mmmm") -> March | O9: =VLOOKUP(ecommerce_customer_data_custom_[[#This Row],[Customer Age]],AgeGroupMapping!$A$2:$C$5,3,TRUE) -> Middle-Aged | P9: =IF(ecommerce_customer_data_custom_[[#This Row],[Returns]]=1,"Returned","Not Returned") -> Not Returned | Q9: =_xlfn.XLOOKUP(ecommerce_customer_data_custom_[[#This Row],[Payment Method]],PaymentMapping!$A$2:$A$11,PaymentMapping!$B$2:$B$11,"Other") -> Cash
A10: 13593 | B10: 43956.843 | C10: Clothing | D10: 182 | E10: 2 | F10: 3363 | G10: PayPal | H10: 49 | I10: 1 | J10: Female | K10: 1 | L10: =YEAR(ecommerce_customer_data_custom_[[#This Row],[Purchase Date]]) -> 2020 | M10: =MONTH(ecommerce_customer_data_custom_[[#This Row],[Purchase Date]]) -> 5 | N10: =TEXT(ecommerce_customer_data_custom_[[#This Row],[Purchase Date]],"mmmm") -> May | O10: =VLOOKUP(ecommerce_customer_data_custom_[[#This Row],[Customer Age]],AgeGroupMapping!$A$2:$C$5,3,TRUE) -> Middle-Aged | P10: =IF(ecommerce_customer_data_custom_[[#This Row],[Returns]]=1,"Returned","Not Returned") -> Returned | Q10: =_xlfn.XLOOKUP(ecommerce_customer_data_custom_[[#This Row],[Payment Method]],PaymentMapping!$A$2:$A$11,PaymentMapping!$B$2:$B$11,"Other") -> Wallet/UPI
A11: 28805 | B11: 45182.183 | C11: Electronics | D11: 394 | E11: 2 | F11: 1993 | G11: Credit Card | H11: 19 | I11: 0 | J11: Male | K11: 0 | L11: =YEAR(ecommerce_customer_data_custom_[[#This Row],[Purchase Date]]) -> 2023 | M11: =MONTH(ecommerce_customer_data_custom_[[#This Row],[Purchase Date]]) -> 9 | N11: =TEXT(ecommerce_customer_data_custom_[[#This Row],[Purchase Date]],"mmmm") -> September | O11: =VLOOKUP(ecommerce_customer_data_custom_[[#This Row],[Customer Age]],AgeGroupMapping!$A$2:$C$5,3,TRUE) -> Young | P11: =IF(ecommerce_customer_data_custom_[[#This Row],[Returns]]=1,"Returned","Not Returned") -> Not Returned | Q11: =_xlfn.XLOOKUP(ecommerce_customer_data_custom_[[#This Row],[Payment Method]],PaymentMapping!$A$2:$A$11,PaymentMapping!$B$2:$B$11,"Other") -> Card
A12: 28805 | B12: 44286.41 | C12: Clothing | D12: 366 | E12: 1 | F12: 246 | G12: PayPal | H12: 19 | I12: 0 | J12: Male | K12: 0 | L12: =YEAR(ecommerce_customer_data_custom_[[#This Row],[Purchase Date]]) -> 2021 | M12: =MONTH(ecommerce_customer_data_custom_[[#This Row],[Purchase Date]]) -> 3 | N12: =TEXT(ecommerce_customer_data_custom_[[#This Row],[Purchase Date]],"mmmm") -> March | O12: =VLOOKUP(ecommerce_customer_data_custom_[[#This Row],[Customer Age]],AgeGroupMapping!$A$2:$C$5,3,TRUE) -> Young | P12: =IF(ecommerce_customer_data_custom_[[#This Row],[Returns]]=1,"Returned","Not Returned") -> Not Returned | Q12: =_xlfn.XLOOKUP(ecommerce_customer_data_custom_[[#This Row],[Payment Method]],PaymentMapping!$A$2:$A$11,PaymentMapping!$B$2:$B$11,"Other") -> Wallet/UPI
A13: 28805 | B13: 44214.946 | C13: Books | D13: 348 | E13: 1 | F13: 2682 | G13: Credit Card | H13: 19 | I13: 1 | J13: Male | K13: 0 | L13: =YEAR(ecommerce_customer_data_custom_[[#This Row],[Purchase Date]]) -> 2021 | M13: =MONTH(ecommerce_customer_data_custom_[[#This Row],[Purchase Date]]) -> 1 | N13: =TEXT(ecommerce_customer_data_custom_[[#This Row],[Purchase Date]],"mmmm") -> January | O13: =VLOOKUP(ecommerce_customer_data_custom_[[#This Row],[Customer Age]],AgeGroupMapping!$A$2:$C$5,3,TRUE) -> Young | P13: =IF(ecommerce_customer_data_custom_[[#This Row],[Returns]]=1,"Returned","Not Returned") -> Returned | Q13: =_xlfn.XLOOKUP(ecommerce_customer_data_custom_[[#This Row],[Payment Method]],PaymentMapping!$A$2:$A$11,PaymentMapping!$B$2:$B$11,"Other") -> Card
... A10001: 13574 | B10001: 44486.025 | C10001: Clothing | D10001: 412 | E10001: 4 | F10001: 4291 | G10001: PayPal | H10001: 27 | I10001: 1 | J10001: Male | K10001: 0 | L10001: =YEAR(ecommerce_customer_data_custom_[[#This Row],[Purchase Date]]) -> 2021 | M10001: =MONTH(ecommerce_customer_data_custom_[[#This Row],[Purchase Date]]) -> 10 | N10001: =TEXT(ecommerce_customer_data_custom_[[#This Row],[Purchase Date]],"mmmm") -> October | O10001: =VLOOKUP(ecommerce_customer_data_custom_[[#This Row],[Customer Age]],AgeGroupMapping!$A$2:$C$5,3,TRUE) -> Adult | P10001: =IF(ecommerce_customer_data_custom_[[#This Row],[Returns]]=1,"Returned","Not Returned") -> Returned | Q10001: =_xlfn.XLOOKUP(ecommerce_customer_data_custom_[[#This Row],[Payment Method]],PaymentMapping!$A$2:$A$11,PaymentMapping!$B$2:$B$11,"Other") -> Wallet/UPI

Sheet AgeGroupMapping
A1: Min Age | B1: Max age | C1: Age Group
A2: 0 | B2: 25 | C2: Young
A3: 26 | B3: 40 | C3: Adult
A4: 41 | B4: 60 | C4: Middle-Aged
A5: 61 | B5: 200 | C5: Senior

Sheet PaymentMapping
A1: Raw Method | B1: Payment Category
A2: Credit Card | B2: Card
A3: Debit Card | B3: Card
A4: Visa | B4: Card
A5: MasterCard | B5: Card
A6: UPI | B6: Wallet/UPI
A7: PayPal | B7: Wallet/UPI
A8: Gpay | B8: Wallet/UPI
A9: Paytm | B9: Wallet/UPI
A10: PhonePe | B10: Wallet/UPI
A11: Cash | B11: Cash

Sheet Pivot_Table
D9: Total Sales By Age | G9: Product Category Performance
D10: Age Group | E10: Sum of Total Purchase Amount | G10: Product | H10: Sum of Total Purchase Amount
D11: Adult | E11: 7437332 | G11: Clothing | H11: 8594432
D12: Middle-Aged | E12: 10316985 | G12: Books | H12: 8215111
D13: Senior | E13: 5310906 | G13: Home | H13: 5307783
D14: Young | E14: 4343823 | G14: Electronics | H14: 5291720
D15: Grand Total | E15: 27409046 | G15: Grand Total | H15: 27409046
D18: Sales By Payment Method | G18: Average Order Value By Age Group
D19: Category | E19: Sum of Total Purchase Amount | G19: Age Group | H19: Average of Total Purchase Amount
D20: Card | E20: 11062698 | G20: Adult | H20: 2690.7858
D21: Cash | E21: 5288295 | G21: Middle-Aged | H21: 2798.965
D22: Other | E22: 2671255 | G22: Senior | H22: 2830.9733
D23: Wallet/UPI | E23: 8386798 | G23: Young | H23: 2594.8763
D24: Grand Total | E24: 27409046 | G24: Grand Total | H24: 2740.9046
D27: Total Sales By Month | G27: Monthly Churn Rate
D28: Month | E28: Sum of Total Purchase Amount | G28: Month | H28: Count of Return Flag
D29: January | E29: 2535196 | G29: 1 | H29: 933
D30: February | E30: 2312831 | G30: 2 | H30: 838
D31: March | E31: 2331410 | G31: 3 | H31: 861
D32: April | E32: 2590834 | G32: 4 | H32: 951
D33: May | E33: 2383214 | G33: 5 | H33: 878
D34: June | E34: 2599134 | G34: 6 | H34: 933
D35: July | E35: 2595554 | G35: 7 | H35: 921
D36: August | E36: 2554817 | G36: 8 | H36: 933
D37: September | E37: 1883618 | G37: 9 | H37: 715
D38: October | E38: 1936774 | G38: 10 | H38: 690
D39: November | E39: 1733755 | G39: 11 | H39: 638
D40: December | E40: 1951909 | G40: 12 | H40: 709
D41: Grand Total | E41: 27409046 | G41: Grand Total | H41: 10000
D44: Return Rate By Orders | G44: Churn Rate VS Non Churn Rate
D45: Returned Orders | E45: Total Orders | G45: Churn | H45: Count of Customer ID
D46: 4092 | E46: 10000 | G46: Not Returned | H46: 5908
G47: Returned | H47: 4092
G48: Grand Total | H48: 10000

Sheet Dashboard
